main.py
setup.py
v2mlx_gml.egg-info/PKG-INFO
v2mlx_gml.egg-info/SOURCES.txt
v2mlx_gml.egg-info/dependency_links.txt
v2mlx_gml.egg-info/requires.txt
v2mlx_gml.egg-info/top_level.txt